dartCCF/__init__.py
dartCCF/__main__.py
dartCCF/analyzer.py
dartCCF/cmd_parser.py
dartCCF/log.py
dart_code_convention_fixer-0.2.1.dist-info/METADATA
dart_code_convention_fixer-0.2.1.dist-info/WHEEL
dart_code_convention_fixer-0.2.1.dist-info/entry_points.txt
dart_code_convention_fixer-0.2.1.dist-info/top_level.txt
dart_code_convention_fixer-0.2.1.dist-info/RECORD
