Metadata-Version: 2.1
Name: dart-code-convention-fixer
Version: 0.2.1
Summary: Dart code convention fixer
Home-page: https://github.com/marynakukhta/metaprog
Author: Kukhta Maryna
Author-email: mskyhta@gmail.com
License: UNKNOWN
Platform: UNKNOWN
